runtimepy/__init__.py
runtimepy/__main__.py
runtimepy/app.py
runtimepy/dev_requirements.txt
runtimepy/entry.py
runtimepy/mapping.py
runtimepy/py.typed
runtimepy/requirements.txt
runtimepy/schemas.py
runtimepy/util.py
runtimepy/channel/__init__.py
runtimepy/channel/registry.py
runtimepy/channel/environment/__init__.py
runtimepy/channel/environment/array.py
runtimepy/channel/environment/base.py
runtimepy/channel/environment/create.py
runtimepy/channel/environment/file.py
runtimepy/channel/environment/sample.py
runtimepy/channel/environment/telemetry.py
runtimepy/channel/environment/command/__init__.py
runtimepy/channel/environment/command/parser.py
runtimepy/channel/environment/command/processor.py
runtimepy/channel/environment/command/result.py
runtimepy/channel/event/__init__.py
runtimepy/channel/event/header.py
runtimepy/codec/__init__.py
runtimepy/codec/protocol/__init__.py
runtimepy/codec/protocol/base.py
runtimepy/codec/protocol/json.py
runtimepy/codec/protocol/receiver.py
runtimepy/codec/system/__init__.py
runtimepy/commands/__init__.py
runtimepy/commands/all.py
runtimepy/commands/arbiter.py
runtimepy/commands/common.py
runtimepy/commands/mtu.py
runtimepy/commands/server.py
runtimepy/commands/task.py
runtimepy/commands/tftp.py
runtimepy/commands/tui.py
runtimepy/control/__init__.py
runtimepy/control/source.py
runtimepy/control/step.py
runtimepy/control/env/__init__.py
runtimepy/data/404.md
runtimepy/data/base.yaml
runtimepy/data/browser.yaml
runtimepy/data/dummy_load.yaml
runtimepy/data/factories.yaml
runtimepy/data/favicon.ico
runtimepy/data/sample_telemetry.yaml
runtimepy/data/server.yaml
runtimepy/data/server_base.yaml
runtimepy/data/server_dev.yaml
runtimepy/data/tftp_server.yaml
runtimepy/data/css/bootstrap_extra.css
runtimepy/data/css/font.css
runtimepy/data/css/main.css
runtimepy/data/js/DataConnection.js
runtimepy/data/js/JsonConnection.js
runtimepy/data/js/audio.js
runtimepy/data/js/events.js
runtimepy/data/js/init.js
runtimepy/data/js/main.js
runtimepy-5.15.8.dist-info/licenses/LICENSE
runtimepy-5.15.8.dist-info/METADATA
runtimepy-5.15.8.dist-info/WHEEL
runtimepy-5.15.8.dist-info/entry_points.txt
runtimepy-5.15.8.dist-info/top_level.txt
runtimepy-5.15.8.dist-info/RECORD
