Metadata-Version: 2.4
Name: runtimepy
Version: 5.15.8
Summary: A framework for implementing Python services.
Home-page: https://github.com/libre-embedded/runtimepy
Author: Libre Embedded
Author-email: Libre Embedded <vaughn@libre-embedded.com>
Maintainer-email: Libre Embedded <vaughn@libre-embedded.com>
License-Expression: MIT
Classifier: Programming Language :: Python :: 3.12
Classifier: Programming Language :: Python :: 3.13
Classifier: Operating System :: Microsoft :: Windows
Classifier: Operating System :: MacOS
Classifier: Operating System :: POSIX :: Linux
Classifier: Operating System :: Unix
Classifier: Development Status :: 5 - Production/Stable
Requires-Python: >=3.12
License-File: LICENSE
Requires-Dist: psutil
Requires-Dist: vcorelib>=3.6.4
Requires-Dist: websockets
Requires-Dist: svgen>=0.8.0
Requires-Dist: aiofiles
Provides-Extra: test
Requires-Dist: pylint; extra == "test"
Requires-Dist: flake8; extra == "test"
Requires-Dist: black; extra == "test"
Requires-Dist: ruff; extra == "test"
Requires-Dist: mypy; extra == "test"
Requires-Dist: isort; extra == "test"
Requires-Dist: yamllint; extra == "test"
Requires-Dist: yambs; extra == "test"
Requires-Dist: vmklib>=2.0.3; extra == "test"
Requires-Dist: sphinx; extra == "test"
Requires-Dist: sphinx-book-theme; extra == "test"
Requires-Dist: pytest-asyncio; extra == "test"
Requires-Dist: pytest-timeout; extra == "test"
Requires-Dist: types-psutil; extra == "test"
Requires-Dist: setuptools-wrapper; extra == "test"
Requires-Dist: types-setuptools; extra == "test"
Requires-Dist: types-requests; extra == "test"
Requires-Dist: uvloop; (sys_platform != "win32" and sys_platform != "cygwin") and extra == "test"
Dynamic: author
Dynamic: home-page
Dynamic: license-file
Dynamic: requires-dist
Dynamic: requires-python
